ParseBuilder/BaseParser.py
ParseBuilder/Builder.py
ParseBuilder/__init__.py
ParseBuilder-1.0.0.dist-info/LICENSE
ParseBuilder-1.0.0.dist-info/METADATA
ParseBuilder-1.0.0.dist-info/WHEEL
ParseBuilder-1.0.0.dist-info/top_level.txt
ParseBuilder-1.0.0.dist-info/RECORD
