Metadata-Version: 2.1
Name: ParseBuilder
Version: 1.0.0
Summary: Library for automatic construction of lexers
Author: Alexander554
Author-email: gaa.28112008@gmail.com
Keywords: parsebuilder python parser
Classifier: Programming Language :: Python :: 3.11
Classifier: License :: OSI Approved :: MIT License
Classifier: Operating System :: OS Independent
Requires-Python: >=3.7
License-File: LICENSE
